sexpdata.py
sexpdata-0.0.4.dist-info/LICENSE
sexpdata-0.0.4.dist-info/METADATA
sexpdata-0.0.4.dist-info/WHEEL
sexpdata-0.0.4.dist-info/top_level.txt
sexpdata-0.0.4.dist-info/RECORD
