Metadata-Version: 2.1
Name: sexpdata
Version: 0.0.4
Summary: S-expression parser for Python
Home-page: https://github.com/jd-boyd/sexpdata
Author: Joshua D. Boyd, Takafumi Arakaki
Author-email: jdboyd@jdboyd.net
License: BSD License
Keywords: s-expression,lisp,parser
Classifier: Development Status :: 3 - Alpha
Classifier: License :: OSI Approved :: BSD License
Classifier: Programming Language :: Python
Classifier: Programming Language :: Python :: 2
Classifier: Programming Language :: Python :: 2.7
Classifier: Programming Language :: Python :: 3
Classifier: Programming Language :: Python :: 3.3
Classifier: Programming Language :: Python :: 3.4
Classifier: Programming Language :: Python :: 3.5
Classifier: Programming Language :: Python :: 3.6
Classifier: Programming Language :: Python :: 3.7
Classifier: Programming Language :: Lisp
Classifier: Programming Language :: Emacs-Lisp
License-File: LICENSE
